{"aviate": {"value": 0}, "biomes": {"value": 33, "rank": 56}, "break_tools": {"value": 79, "rank": 4}, "breed": {"value": 1, "rank": 90}, "climb": {"value": 543136, "rank": 30}, "collect_berries": {"value": 12, "rank": 121}, "collect_shroom": {"value": 91, "rank": 6}, "craft_armor": {"value": 124, "rank": 9}, "craft_beacon": {"value": 0}, "craft_bookshelf": {"value": 10, "rank": 53}, "craft_bread": {"value": 796, "rank": 7}, "craft_bundle": {"value": 0}, "craft_clock": {"value": 0}, "craft_compass": {"value": 0}, "craft_ender_chest": {"value": 3, "rank": 12}, "craft_glowstone": {"value": 13, "rank": 29}, "craft_mineral_block": {"value": 104, "rank": 67}, "craft_paper": {"value": 6, "rank": 101}, "craft_recovery_compass": {"value": 0}, "craft_respawn_anchor": {"value": 0}, "craft_sponge": {"value": 0}, "craft_spyglass": {"value": 1, "rank": 24}, "craft_sword": {"value": 49, "rank": 1}, "craft_tnt": {"value": 222, "rank": 22}, "craft_tools": {"value": 203, "rank": 4}, "craft_turtle_helmet": {"value": 0}, "craft_wool": {"value": 21, "rank": 53}, "crouch": {"value": 423944, "rank": 39}, "damage_dealt": {"value": 180209, "rank": 44}, "damage_shield": {"value": 3469, "rank": 76}, "damage_taken": {"value": 308291, "rank": 13}, "death": {"value": 557, "rank": 12}, "dive": {"value": 645459, "rank": 42}, "drink_milk": {"value": 0}, "drop": {"value": 5809, "rank": 10}, "eat_cookie": {"value": 24, "rank": 10}, "eat_fish": {"value": 0}, "eat_junkfood": {"value": 215, "rank": 4}, "eat_meat": {"value": 32, "rank": 97}, "eat_rawmeat": {"value": 8, "rank": 41}, "eat_soup": {"value": 1, "rank": 24}, "eat_veggie": {"value": 3331, "rank": 8}, "enchant": {"value": 1, "rank": 79}, "fall": {"value": 3005831, "rank": 21}, "harvest_bamboo": {"value": 75, "rank": 64}, "harvest_nether_wart": {"value": 6280, "rank": 2}, "harvest_sugar": {"value": 380, "rank": 47}, "interact_anvil": {"value": 78, "rank": 32}, "interact_blast_furnace": {"value": 12, "rank": 30}, "interact_brewing_stand": {"value": 152, "rank": 11}, "interact_campfire": {"value": 3, "rank": 33}, "interact_cartography": {"value": 3, "rank": 20}, "interact_grindstone": {"value": 1, "rank": 101}, "interact_lectern": {"value": 0}, "interact_loom": {"value": 1, "rank": 41}, "interact_smoker": {"value": 275, "rank": 1}, "interact_stonecutter": {"value": 6, "rank": 51}, "jump": {"value": 112385, "rank": 17}, "kill_any": {"value": 5501, "rank": 63}, "kill_blaze": {"value": 0}, "kill_creeper": {"value": 1655, "rank": 2}, "kill_endermite": {"value": 0}, "kill_ender_dragon": {"value": 0}, "kill_ghast": {"value": 0}, "kill_magma_cube": {"value": 0}, "kill_phantom": {"value": 3, "rank": 77}, "kill_ravager": {"value": 0}, "kill_shulker": {"value": 0}, "kill_silverfish": {"value": 0}, "kill_slime": {"value": 1, "rank": 80}, "kill_vex": {"value": 0}, "kill_warden": {"value": 0}, "kill_witch": {"value": 21, "rank": 26}, "kill_wither_skeleton": {"value": 0}, "kill_bee": {"value": 0}, "kill_dolphin": {"value": 0}, "kill_enderman": {"value": 3, "rank": 114}, "kill_goat": {"value": 0}, "kill_iron_golem": {"value": 2, "rank": 40}, "kill_panda": {"value": 0}, "kill_piglin": {"value": 0}, "kill_polar_bear": {"value": 0}, "kill_snow_golem": {"value": 1, "rank": 6}, "kill_zombie_pigman": {"value": 0}, "kill_zombified_piglin": {"value": 4, "rank": 74}, "kill_piglin_brute": {"value": 0}, "kill_allay": {"value": 0}, "kill_axolotl": {"value": 0}, "kill_bat": {"value": 1, "rank": 28}, "kill_chicken": {"value": 7, "rank": 55}, "kill_cow": {"value": 7, "rank": 76}, "kill_horse": {"value": 3, "rank": 30}, "kill_fox": {"value": 0}, "kill_frog": {"value": 1, "rank": 9}, "kill_mooshroom": {"value": 0}, "kill_parrot": {"value": 0}, "kill_pig": {"value": 22, "rank": 23}, "kill_rabbit": {"value": 0}, "kill_sheep": {"value": 8, "rank": 64}, "kill_strider": {"value": 0}, "kill_tadpole": {"value": 0}, "kill_turtle": {"value": 0}, "kill_villager": {"value": 0}, "kill_wandering_trader": {"value": 0}, "kill_wolf": {"value": 0}, "kill_ocelot": {"value": 0}, "kill_llama": {"value": 0}, "kill_zombie": {"value": 1926, "rank": 5}, "kill_skeleton": {"value": 1718, "rank": 2}, "kill_spider": {"value": 54, "rank": 37}, "kill_guardian": {"value": 0}, "kill_illagers": {"value": 0}, "kill_hoglins": {"value": 0}, "kill_fish": {"value": 0}, "kill_squid": {"value": 0}, "killed_by_creeper": {"value": 54, "rank": 4}, "killed_by_warden": {"value": 0}, "mine_amethyst": {"value": 6, "rank": 38}, "mine_cobweb": {"value": 11, "rank": 52}, "mine_coral": {"value": 0}, "mine_dimensional": {"value": 1263, "rank": 74}, "mine_glass": {"value": 905, "rank": 5}, "mine_grass": {"value": 213, "rank": 62}, "mine_ground": {"value": 2389, "rank": 45}, "mine_ice": {"value": 190, "rank": 31}, "mine_kelp": {"value": 83, "rank": 13}, "mine_nether_foliage": {"value": 0}, "mine_obsidian": {"value": 126, "rank": 31}, "mine_ancient_debris": {"value": 5, "rank": 62}, "mine_coal_ore": {"value": 343, "rank": 28}, "mine_iron_ore": {"value": 220, "rank": 31}, "mine_copper_ore": {"value": 52, "rank": 60}, "mine_diamond_ore": {"value": 32, "rank": 56}, "mine_gold_ore": {"value": 64, "rank": 66}, "mine_emerald_ore": {"value": 2, "rank": 32}, "mine_lapis_ore": {"value": 47, "rank": 28}, "mine_redstone_ore": {"value": 172, "rank": 16}, "mine_nether_quartz_ore": {"value": 86, "rank": 64}, "mine_pointed_dripstone": {"value": 2, "rank": 64}, "mine_snow": {"value": 127, "rank": 15}, "mine_spawner": {"value": 1, "rank": 73}, "mine_stone": {"value": 3513, "rank": 67}, "mine_wood": {"value": 1045, "rank": 41}, "noteblock": {"value": 0}, "open_container": {"value": 9236, "rank": 13}, "place_banner": {"value": 4, "rank": 38}, "place_bars": {"value": 0}, "place_cactus": {"value": 0}, "place_candle": {"value": 5, "rank": 11}, "place_chorus_flower": {"value": 0}, "place_conveyor": {"value": 23, "rank": 52}, "place_electrics": {"value": 891, "rank": 16}, "place_glass": {"value": 7166, "rank": 3}, "place_lantern": {"value": 2, "rank": 59}, "place_lightning_rod": {"value": 1, "rank": 29}, "place_lodestone": {"value": 0}, "place_piston": {"value": 212, "rank": 13}, "place_rails": {"value": 141, "rank": 56}, "place_sapling": {"value": 105, "rank": 43}, "place_scaffolding": {"value": 0}, "place_sign": {"value": 175, "rank": 8}, "place_stairs": {"value": 87, "rank": 75}, "place_torch": {"value": 749, "rank": 30}, "place_wall": {"value": 163, "rank": 39}, "play": {"value": 4985024, "rank": 44}, "play_record": {"value": 0}, "pot_flower": {"value": 0}, "ride_boat": {"value": 2043693, "rank": 30}, "ride_horse": {"value": 1763, "rank": 82}, "ride_minecart": {"value": 19067, "rank": 79}, "ride_pig": {"value": 0}, "ride_strider": {"value": 0}, "ring_bell": {"value": 5, "rank": 59}, "sleep": {"value": 10, "rank": 86}, "sprint": {"value": 7657676, "rank": 42}, "swim": {"value": 357157, "rank": 46}, "time_since_death": {"value": 13739, "rank": 134}, "time_since_sleep": {"value": 13759, "rank": 124}, "trade": {"value": 835, "rank": 29}, "trigger_raid": {"value": 0}, "use_book": {"value": 0}, "use_bow": {"value": 1478, "rank": 10}, "use_crossbow": {"value": 0}, "use_dirt": {"value": 1356, "rank": 41}, "use_egg": {"value": 0}, "use_ender_eye": {"value": 0}, "use_ender_pearl": {"value": 1, "rank": 128}, "use_fireworks": {"value": 0}, "use_flint": {"value": 260, "rank": 9}, "use_goat_horn": {"value": 0}, "use_hoe": {"value": 491, "rank": 34}, "use_honey_bottle": {"value": 0}, "use_lava_bucket": {"value": 24, "rank": 47}, "use_potion": {"value": 31, "rank": 22}, "use_shears": {"value": 11, "rank": 71}, "use_snowball": {"value": 156, "rank": 2}, "use_totem": {"value": 0}, "use_water_bucket": {"value": 410, "rank": 23}, "walk": {"value": 17999850, "rank": 21}, "walk_on_water": {"value": 942001, "rank": 31}, "win_raid": {"value": 0}}