{"aviate": {"value": 41759376, "rank": 20}, "biomes": {"value": 47, "rank": 17}, "break_tools": {"value": 25, "rank": 30}, "breed": {"value": 28, "rank": 31}, "climb": {"value": 3912286, "rank": 1}, "collect_berries": {"value": 124, "rank": 37}, "collect_shroom": {"value": 25, "rank": 23}, "craft_armor": {"value": 48, "rank": 15}, "craft_beacon": {"value": 1, "rank": 20}, "craft_bookshelf": {"value": 251, "rank": 1}, "craft_bread": {"value": 179, "rank": 32}, "craft_bundle": {"value": 0}, "craft_clock": {"value": 0}, "craft_compass": {"value": 9, "rank": 7}, "craft_ender_chest": {"value": 0}, "craft_glowstone": {"value": 41, "rank": 15}, "craft_mineral_block": {"value": 910, "rank": 25}, "craft_paper": {"value": 3474, "rank": 13}, "craft_recovery_compass": {"value": 0}, "craft_respawn_anchor": {"value": 0}, "craft_sponge": {"value": 60, "rank": 5}, "craft_spyglass": {"value": 0}, "craft_sword": {"value": 14, "rank": 15}, "craft_tnt": {"value": 8, "rank": 41}, "craft_tools": {"value": 107, "rank": 9}, "craft_turtle_helmet": {"value": 0}, "craft_wool": {"value": 935, "rank": 5}, "crouch": {"value": 3872773, "rank": 6}, "damage_dealt": {"value": 768572, "rank": 7}, "damage_shield": {"value": 78549, "rank": 1}, "damage_taken": {"value": 736798, "rank": 1}, "death": {"value": 1394, "rank": 1}, "dive": {"value": 2161483, "rank": 8}, "drink_milk": {"value": 0}, "drop": {"value": 3126, "rank": 16}, "eat_cookie": {"value": 0}, "eat_fish": {"value": 830, "rank": 4}, "eat_junkfood": {"value": 37, "rank": 22}, "eat_meat": {"value": 1277, "rank": 3}, "eat_rawmeat": {"value": 23, "rank": 14}, "eat_soup": {"value": 0}, "eat_veggie": {"value": 2995, "rank": 7}, "enchant": {"value": 35, "rank": 28}, "fall": {"value": 7451937, "rank": 3}, "harvest_bamboo": {"value": 232, "rank": 38}, "harvest_nether_wart": {"value": 16, "rank": 55}, "harvest_sugar": {"value": 1204, "rank": 23}, "interact_anvil": {"value": 122, "rank": 14}, "interact_blast_furnace": {"value": 6, "rank": 40}, "interact_brewing_stand": {"value": 18, "rank": 38}, "interact_campfire": {"value": 4, "rank": 29}, "interact_cartography": {"value": 6, "rank": 6}, "interact_grindstone": {"value": 10, "rank": 49}, "interact_lectern": {"value": 0}, "interact_loom": {"value": 4, "rank": 17}, "interact_smoker": {"value": 1, "rank": 71}, "interact_stonecutter": {"value": 143, "rank": 4}, "jump": {"value": 228734, "rank": 5}, "kill_any": {"value": 22601, "rank": 17}, "kill_blaze": {"value": 33, "rank": 20}, "kill_creeper": {"value": 30, "rank": 34}, "kill_endermite": {"value": 4, "rank": 13}, "kill_ender_dragon": {"value": 0}, "kill_ghast": {"value": 4, "rank": 20}, "kill_magma_cube": {"value": 266, "rank": 4}, "kill_phantom": {"value": 87, "rank": 15}, "kill_ravager": {"value": 1, "rank": 29}, "kill_shulker": {"value": 0}, "kill_silverfish": {"value": 7, "rank": 9}, "kill_slime": {"value": 39, "rank": 20}, "kill_vex": {"value": 0}, "kill_warden": {"value": 0}, "kill_witch": {"value": 10, "rank": 27}, "kill_wither_skeleton": {"value": 37, "rank": 26}, "kill_bee": {"value": 0}, "kill_dolphin": {"value": 0}, "kill_enderman": {"value": 18642, "rank": 5}, "kill_goat": {"value": 0}, "kill_iron_golem": {"value": 13, "rank": 7}, "kill_panda": {"value": 0}, "kill_piglin": {"value": 53, "rank": 9}, "kill_polar_bear": {"value": 0}, "kill_snow_golem": {"value": 0}, "kill_zombie_pigman": {"value": 0}, "kill_zombified_piglin": {"value": 255, "rank": 23}, "kill_piglin_brute": {"value": 0}, "kill_allay": {"value": 0}, "kill_axolotl": {"value": 0}, "kill_bat": {"value": 0}, "kill_chicken": {"value": 10, "rank": 31}, "kill_cow": {"value": 70, "rank": 7}, "kill_horse": {"value": 1, "rank": 52}, "kill_fox": {"value": 0}, "kill_frog": {"value": 0}, "kill_mooshroom": {"value": 0}, "kill_parrot": {"value": 0}, "kill_pig": {"value": 86, "rank": 3}, "kill_rabbit": {"value": 0}, "kill_sheep": {"value": 72, "rank": 4}, "kill_strider": {"value": 0}, "kill_tadpole": {"value": 0}, "kill_turtle": {"value": 2, "rank": 18}, "kill_villager": {"value": 24, "rank": 14}, "kill_wandering_trader": {"value": 6, "rank": 2}, "kill_wolf": {"value": 0}, "kill_ocelot": {"value": 1, "rank": 10}, "kill_llama": {"value": 13, "rank": 3}, "kill_zombie": {"value": 588, "rank": 19}, "kill_skeleton": {"value": 147, "rank": 18}, "kill_spider": {"value": 123, "rank": 10}, "kill_guardian": {"value": 0}, "kill_illagers": {"value": 112, "rank": 30}, "kill_hoglins": {"value": 29, "rank": 8}, "kill_fish": {"value": 6, "rank": 21}, "kill_squid": {"value": 2, "rank": 37}, "killed_by_creeper": {"value": 71, "rank": 2}, "killed_by_warden": {"value": 45, "rank": 10}, "mine_amethyst": {"value": 0}, "mine_cobweb": {"value": 39, "rank": 26}, "mine_coral": {"value": 44, "rank": 13}, "mine_dimensional": {"value": 21235, "rank": 15}, "mine_glass": {"value": 154, "rank": 28}, "mine_grass": {"value": 255, "rank": 51}, "mine_ground": {"value": 5337, "rank": 27}, "mine_ice": {"value": 146, "rank": 31}, "mine_kelp": {"value": 150, "rank": 7}, "mine_nether_foliage": {"value": 4, "rank": 30}, "mine_obsidian": {"value": 201, "rank": 25}, "mine_ancient_debris": {"value": 1, "rank": 71}, "mine_coal_ore": {"value": 415, "rank": 20}, "mine_iron_ore": {"value": 180, "rank": 34}, "mine_copper_ore": {"value": 166, "rank": 18}, "mine_diamond_ore": {"value": 59, "rank": 28}, "mine_gold_ore": {"value": 98, "rank": 39}, "mine_emerald_ore": {"value": 1, "rank": 43}, "mine_lapis_ore": {"value": 40, "rank": 30}, "mine_redstone_ore": {"value": 223, "rank": 7}, "mine_nether_quartz_ore": {"value": 1631, "rank": 6}, "mine_pointed_dripstone": {"value": 2, "rank": 58}, "mine_snow": {"value": 390, "rank": 5}, "mine_spawner": {"value": 1, "rank": 60}, "mine_stone": {"value": 19339, "rank": 12}, "mine_wood": {"value": 11162, "rank": 1}, "noteblock": {"value": 356, "rank": 8}, "open_container": {"value": 8185, "rank": 13}, "place_banner": {"value": 17, "rank": 16}, "place_bars": {"value": 27, "rank": 17}, "place_cactus": {"value": 28, "rank": 7}, "place_candle": {"value": 0}, "place_chorus_flower": {"value": 0}, "place_conveyor": {"value": 360, "rank": 13}, "place_electrics": {"value": 832, "rank": 14}, "place_glass": {"value": 1277, "rank": 18}, "place_lantern": {"value": 65, "rank": 11}, "place_lightning_rod": {"value": 11, "rank": 5}, "place_lodestone": {"value": 0}, "place_piston": {"value": 101, "rank": 18}, "place_rails": {"value": 2189, "rank": 4}, "place_sapling": {"value": 196, "rank": 26}, "place_scaffolding": {"value": 1127, "rank": 2}, "place_sign": {"value": 242, "rank": 3}, "place_stairs": {"value": 3151, "rank": 4}, "place_torch": {"value": 2652, "rank": 5}, "place_wall": {"value": 498, "rank": 12}, "play": {"value": 19532960, "rank": 7}, "play_record": {"value": 0}, "pot_flower": {"value": 0}, "ride_boat": {"value": 5735943, "rank": 4}, "ride_horse": {"value": 1745, "rank": 75}, "ride_minecart": {"value": 545882, "rank": 22}, "ride_pig": {"value": 0}, "ride_strider": {"value": 0}, "ring_bell": {"value": 213, "rank": 5}, "sleep": {"value": 124, "rank": 5}, "sprint": {"value": 31081683, "rank": 6}, "swim": {"value": 3102960, "rank": 5}, "time_since_death": {"value": 2421, "rank": 200}, "time_since_sleep": {"value": 2441, "rank": 194}, "trade": {"value": 1218, "rank": 19}, "trigger_raid": {"value": 4, "rank": 22}, "use_book": {"value": 0}, "use_bow": {"value": 160, "rank": 40}, "use_crossbow": {"value": 27, "rank": 21}, "use_dirt": {"value": 4383, "rank": 14}, "use_egg": {"value": 31, "rank": 7}, "use_ender_eye": {"value": 0}, "use_ender_pearl": {"value": 512, "rank": 6}, "use_fireworks": {"value": 740, "rank": 31}, "use_flint": {"value": 81, "rank": 28}, "use_goat_horn": {"value": 0}, "use_hoe": {"value": 833, "rank": 19}, "use_honey_bottle": {"value": 0}, "use_lava_bucket": {"value": 485, "rank": 3}, "use_potion": {"value": 8, "rank": 37}, "use_shears": {"value": 467, "rank": 16}, "use_snowball": {"value": 23, "rank": 10}, "use_totem": {"value": 0}, "use_water_bucket": {"value": 1870, "rank": 3}, "walk": {"value": 51893394, "rank": 3}, "walk_on_water": {"value": 2206202, "rank": 6}, "win_raid": {"value": 0}}