{"aviate": {"value": 85233183, "rank": 1}, "biomes": {"value": 46, "rank": 2}, "break_tools": {"value": 4, "rank": 34}, "breed": {"value": 40, "rank": 6}, "climb": {"value": 99755, "rank": 14}, "collect_berries": {"value": 0}, "collect_shroom": {"value": 19, "rank": 4}, "craft_armor": {"value": 62, "rank": 3}, "craft_beacon": {"value": 20, "rank": 1}, "craft_bookshelf": {"value": 50, "rank": 3}, "craft_bread": {"value": 3298, "rank": 1}, "craft_bundle": {"value": 0}, "craft_clock": {"value": 0}, "craft_compass": {"value": 0}, "craft_ender_chest": {"value": 0}, "craft_glowstone": {"value": 32, "rank": 2}, "craft_mineral_block": {"value": 9386, "rank": 1}, "craft_paper": {"value": 1359, "rank": 3}, "craft_recovery_compass": {"value": 0}, "craft_respawn_anchor": {"value": 0}, "craft_sponge": {"value": 0}, "craft_spyglass": {"value": 0}, "craft_sword": {"value": 7, "rank": 9}, "craft_tnt": {"value": 696, "rank": 1}, "craft_tools": {"value": 46, "rank": 10}, "craft_turtle_helmet": {"value": 0}, "craft_wool": {"value": 20, "rank": 9}, "crouch": {"value": 6758847, "rank": 1}, "damage_dealt": {"value": 1042333, "rank": 1}, "damage_shield": {"value": 14120, "rank": 7}, "damage_taken": {"value": 156268, "rank": 1}, "death": {"value": 61, "rank": 23}, "dive": {"value": 506400, "rank": 4}, "drink_milk": {"value": 2, "rank": 3}, "drop": {"value": 4760, "rank": 1}, "eat_cookie": {"value": 0}, "eat_fish": {"value": 18, "rank": 8}, "eat_junkfood": {"value": 0}, "eat_meat": {"value": 194, "rank": 3}, "eat_rawmeat": {"value": 2, "rank": 18}, "eat_soup": {"value": 1, "rank": 5}, "eat_veggie": {"value": 1720, "rank": 2}, "enchant": {"value": 13, "rank": 6}, "fall": {"value": 1489759, "rank": 1}, "harvest_bamboo": {"value": 1489, "rank": 6}, "harvest_nether_wart": {"value": 136, "rank": 5}, "harvest_sugar": {"value": 1447, "rank": 4}, "interact_anvil": {"value": 117, "rank": 2}, "interact_blast_furnace": {"value": 74, "rank": 1}, "interact_brewing_stand": {"value": 195, "rank": 1}, "interact_campfire": {"value": 0}, "interact_cartography": {"value": 0}, "interact_grindstone": {"value": 14, "rank": 6}, "interact_lectern": {"value": 0}, "interact_loom": {"value": 0}, "interact_smoker": {"value": 67, "rank": 2}, "interact_stonecutter": {"value": 8, "rank": 5}, "jump": {"value": 69170, "rank": 2}, "kill_any": {"value": 205224, "rank": 1}, "kill_blaze": {"value": 347, "rank": 1}, "kill_creeper": {"value": 23, "rank": 5}, "kill_endermite": {"value": 0}, "kill_ender_dragon": {"value": 1, "rank": 1}, "kill_ghast": {"value": 20, "rank": 1}, "kill_magma_cube": {"value": 459, "rank": 1}, "kill_phantom": {"value": 97, "rank": 2}, "kill_ravager": {"value": 0}, "kill_shulker": {"value": 45, "rank": 1}, "kill_silverfish": {"value": 1, "rank": 4}, "kill_slime": {"value": 106, "rank": 1}, "kill_vex": {"value": 2, "rank": 1}, "kill_warden": {"value": 0}, "kill_witch": {"value": 13493, "rank": 1}, "kill_wither_skeleton": {"value": 5739, "rank": 1}, "kill_bee": {"value": 0}, "kill_dolphin": {"value": 0}, "kill_enderman": {"value": 4678, "rank": 2}, "kill_goat": {"value": 0}, "kill_iron_golem": {"value": 0}, "kill_panda": {"value": 0}, "kill_piglin": {"value": 147, "rank": 1}, "kill_polar_bear": {"value": 0}, "kill_snow_golem": {"value": 0}, "kill_zombie_pigman": {"value": 0}, "kill_zombified_piglin": {"value": 38099, "rank": 1}, "kill_piglin_brute": {"value": 9, "rank": 1}, "kill_allay": {"value": 0}, "kill_axolotl": {"value": 0}, "kill_bat": {"value": 0}, "kill_chicken": {"value": 8, "rank": 13}, "kill_cow": {"value": 42, "rank": 7}, "kill_horse": {"value": 0}, "kill_fox": {"value": 0}, "kill_frog": {"value": 0}, "kill_mooshroom": {"value": 0}, "kill_parrot": {"value": 1, "rank": 1}, "kill_pig": {"value": 15, "rank": 10}, "kill_rabbit": {"value": 0}, "kill_sheep": {"value": 19, "rank": 10}, "kill_strider": {"value": 0}, "kill_tadpole": {"value": 0}, "kill_turtle": {"value": 0}, "kill_villager": {"value": 19, "rank": 4}, "kill_wandering_trader": {"value": 1, "rank": 2}, "kill_wolf": {"value": 0}, "kill_ocelot": {"value": 0}, "kill_llama": {"value": 2, "rank": 3}, "kill_zombie": {"value": 608, "rank": 1}, "kill_skeleton": {"value": 193, "rank": 1}, "kill_spider": {"value": 97, "rank": 3}, "kill_guardian": {"value": 0}, "kill_illagers": {"value": 128217, "rank": 1}, "kill_hoglins": {"value": 3, "rank": 5}, "kill_fish": {"value": 1, "rank": 7}, "kill_squid": {"value": 0}, "killed_by_creeper": {"value": 0}, "killed_by_warden": {"value": 1, "rank": 11}, "mine_amethyst": {"value": 6, "rank": 4}, "mine_cobweb": {"value": 25, "rank": 4}, "mine_coral": {"value": 16, "rank": 6}, "mine_dimensional": {"value": 43290, "rank": 1}, "mine_glass": {"value": 650, "rank": 1}, "mine_grass": {"value": 696, "rank": 2}, "mine_ground": {"value": 17638, "rank": 1}, "mine_ice": {"value": 131, "rank": 3}, "mine_kelp": {"value": 0}, "mine_nether_foliage": {"value": 21, "rank": 1}, "mine_obsidian": {"value": 1587, "rank": 2}, "mine_ancient_debris": {"value": 48, "rank": 1}, "mine_coal_ore": {"value": 215, "rank": 12}, "mine_iron_ore": {"value": 112, "rank": 20}, "mine_copper_ore": {"value": 6, "rank": 32}, "mine_diamond_ore": {"value": 99, "rank": 3}, "mine_gold_ore": {"value": 118, "rank": 6}, "mine_emerald_ore": {"value": 1, "rank": 12}, "mine_lapis_ore": {"value": 46, "rank": 3}, "mine_redstone_ore": {"value": 169, "rank": 2}, "mine_nether_quartz_ore": {"value": 563, "rank": 4}, "mine_pointed_dripstone": {"value": 6, "rank": 7}, "mine_snow": {"value": 1104, "rank": 1}, "mine_spawner": {"value": 10, "rank": 1}, "mine_stone": {"value": 4540, "rank": 10}, "mine_wood": {"value": 2979, "rank": 1}, "noteblock": {"value": 23, "rank": 9}, "open_container": {"value": 9194, "rank": 1}, "place_banner": {"value": 5, "rank": 3}, "place_bars": {"value": 51, "rank": 2}, "place_cactus": {"value": 1, "rank": 3}, "place_candle": {"value": 0}, "place_chorus_flower": {"value": 0}, "place_conveyor": {"value": 760, "rank": 1}, "place_electrics": {"value": 2886, "rank": 1}, "place_glass": {"value": 3219, "rank": 1}, "place_lantern": {"value": 0}, "place_lightning_rod": {"value": 1, "rank": 6}, "place_lodestone": {"value": 0}, "place_piston": {"value": 469, "rank": 1}, "place_rails": {"value": 1554, "rank": 1}, "place_sapling": {"value": 17, "rank": 22}, "place_scaffolding": {"value": 151, "rank": 8}, "place_sign": {"value": 71, "rank": 1}, "place_stairs": {"value": 301, "rank": 3}, "place_torch": {"value": 249, "rank": 23}, "place_wall": {"value": 145, "rank": 5}, "play": {"value": 12340389, "rank": 1}, "play_record": {"value": 0}, "pot_flower": {"value": 0}, "ride_boat": {"value": 2867550, "rank": 5}, "ride_horse": {"value": 8481, "rank": 16}, "ride_minecart": {"value": 0}, "ride_pig": {"value": 0}, "ride_strider": {"value": 0}, "ring_bell": {"value": 0}, "sleep": {"value": 106, "rank": 2}, "sprint": {"value": 13161099, "rank": 1}, "swim": {"value": 511827, "rank": 6}, "time_since_death": {"value": 766277, "rank": 1}, "time_since_sleep": {"value": 116907, "rank": 4}, "trade": {"value": 1669, "rank": 2}, "trigger_raid": {"value": 4113, "rank": 1}, "use_book": {"value": 0}, "use_bow": {"value": 915, "rank": 2}, "use_crossbow": {"value": 0}, "use_dirt": {"value": 3997, "rank": 1}, "use_egg": {"value": 0}, "use_ender_eye": {"value": 13, "rank": 4}, "use_ender_pearl": {"value": 65, "rank": 1}, "use_fireworks": {"value": 2956, "rank": 1}, "use_flint": {"value": 172, "rank": 1}, "use_goat_horn": {"value": 0}, "use_hoe": {"value": 319, "rank": 10}, "use_honey_bottle": {"value": 0}, "use_lava_bucket": {"value": 84, "rank": 4}, "use_potion": {"value": 63, "rank": 1}, "use_shears": {"value": 294, "rank": 5}, "use_snowball": {"value": 14, "rank": 3}, "use_totem": {"value": 0}, "use_water_bucket": {"value": 776, "rank": 1}, "walk": {"value": 9059897, "rank": 5}, "walk_on_water": {"value": 415177, "rank": 5}, "win_raid": {"value": 1255, "rank": 1}}